metadata/__init__.py
metadata/latest/__init__.py
metadata/latest/example.py
metadata/latest/schema.py
metadata/latest/template.py
metadata/metaschema/__init__.py
metadata/metaschema/draft07/__init__.py
metadata/metaschema/draft07/schema.py
metadata/v130/__init__.py
metadata/v130/example.py
metadata/v130/schema.py
metadata/v130/template.py
metadata/v140/__init__.py
metadata/v140/example.py
metadata/v140/schema.py
metadata/v140/template.py
metadata/v141/__init__.py
metadata/v141/example.py
metadata/v141/schema.py
metadata/v141/template.py
metadata/v150/__init__.py
metadata/v150/example.py
metadata/v150/schema.py
metadata/v150/template.py
tests/metadata/__init__.py
tests/metadata/metaschema/__init__.py
tests/metadata/metaschema/draft07/__init__.py
tests/metadata/metaschema/draft07/test_schema.py
tests/metadata/v130/__init__.py
tests/metadata/v130/test_example.py
tests/metadata/v130/test_schema.py
tests/metadata/v130/test_template.py
tests/metadata/v140/__init__.py
tests/metadata/v140/test_example.py
tests/metadata/v140/test_schema.py
tests/metadata/v140/test_template.py
tests/metadata/v141/__init__.py
tests/metadata/v141/test_example.py
tests/metadata/v141/test_schema.py
tests/metadata/v141/test_template.py
tests/metadata/v150/__init__.py
tests/metadata/v150/test_example.py
tests/metadata/v150/test_schema.py
tests/metadata/v150/test_template.py
oep_metadata-1.5.0.dist-info/LICENSE
oep_metadata-1.5.0.dist-info/METADATA
oep_metadata-1.5.0.dist-info/WHEEL
oep_metadata-1.5.0.dist-info/top_level.txt
oep_metadata-1.5.0.dist-info/RECORD
