Metadata-Version: 2.1
Name: oep-metadata
Version: 1.5.0
Summary: Open Energy Platform (OEP) - metadata schemas, examples and templates package
Home-page: https://github.com/OpenEnergyPlatform/oemetadata
Author: Alexis Michaltsis
Author-email: a.michaltsis@rl-institut.de
License: MIT
Keywords: JSON metadata schema open energy platform oep
Platform: UNKNOWN
Classifier: Intended Audience :: Developers
Classifier: License :: OSI Approved :: MIT License
Classifier: Programming Language :: Python :: 3
Classifier: Programming Language :: Python :: 3.9
Requires-Python: >=3.6
